{
  "name": "Example Site",
  "formspark_id": "mLhlpeBjL",
  "botpoison_public_key": "pk_bbb182a9-1ff3-4d9a-839c-06e45f41a6e6",
  "url": "https://example.chobble.com",
  "socials": {
    "facebook": "https://example.chobble.com",
    "instagram": "https://example.chobble.com",
    "tiktok": "https://example.chobble.com",
    "google": "https://example.chobble.com",
    "whatsapp": "https://example.chobble.com",
    "rss": "/feed.xml"
  },
  "sticky_mobile_nav": true,
  "template_repo_url": "https://git.chobble.com/chobble/chobble-template"
}
